entrancebar/__init__.py
entrancebar-0.0.22.dist-info/LICENSE
entrancebar-0.0.22.dist-info/METADATA
entrancebar-0.0.22.dist-info/WHEEL
entrancebar-0.0.22.dist-info/top_level.txt
entrancebar-0.0.22.dist-info/RECORD
