Metadata-Version: 2.1
Name: entrancebar
Version: 0.0.22
Summary: importext
Home-page: UNKNOWN
Author: Chenwe_i_lin
Author-email: 1846913566@qq.com
License: UNKNOWN
Platform: UNKNOWN
Classifier: Programming Language :: Python :: 3
Classifier: License :: OSI Approved :: MIT License
Classifier: Operating System :: OS Independent
